gr_xs/__init__.py
gr_xs/gr_xs.py
gr_xs-0.1.3.dist-info/LICENSE
gr_xs-0.1.3.dist-info/METADATA
gr_xs-0.1.3.dist-info/WHEEL
gr_xs-0.1.3.dist-info/top_level.txt
gr_xs-0.1.3.dist-info/RECORD
